dabbler/__init__.py
dabbler/common.py
dabbler/db_stuff.py
dabbler/ext.py
dabbler/ext_classes.py
dabbler/ext_debug.py
dabbler/gui_compenents.py
dabbler/gui_main.py
dabbler/gui_stuff.py
dabbler/gui_table.py
dabbler/test_parser_gui.py
dabbler/txt_util.py
dabbler/lsp/__init__.py
dabbler/lsp/__main__.py
dabbler/lsp/completer.py
dabbler/lsp/completion_utils.py
dabbler/lsp/db_data.py
dabbler/lsp/duckdb.lark
dabbler/lsp/functions.json
dabbler/lsp/new_parser.py
dabbler/lsp/parser.py
dabbler/lsp/server.py
dabbler/lsp/server_classes.py
dabbler/lsp/sql_utils.py
dabbler/lsp/tst.json
dabbler-0.8.1.2.dist-info/LICENSE.txt
dabbler-0.8.1.2.dist-info/METADATA
dabbler-0.8.1.2.dist-info/WHEEL
dabbler-0.8.1.2.dist-info/top_level.txt
dabbler-0.8.1.2.dist-info/RECORD
