Metadata-Version: 2.1
Name: dabbler
Version: 0.8.1.2
Summary: A qt-gui tool to view database tables/queries integrated within an jupyter/ipython session
Author-email: Ryan DeWitt <ryan.w.dewitt@gmail.com>
License: The MIT License (MIT)
Project-URL: Homepage, https://github.com/ryanwd123/dabbler
Keywords: DuckDB,SQL,autocomplete,intellisense,lsp,language server,gui
Classifier: Development Status :: 3 - Alpha
Classifier: Intended Audience :: Developers
Classifier: License :: OSI Approved :: MIT License
Classifier: Operating System :: OS Independent
Classifier: Programming Language :: Python :: 3
Classifier: Topic :: Database
Classifier: Topic :: Software Development
Requires-Python: >=3.9
License-File: LICENSE.txt
Requires-Dist: duckdb
Requires-Dist: qtpy
Requires-Dist: sqlparse
Requires-Dist: sqlglot
Requires-Dist: lark
Requires-Dist: pygls
Requires-Dist: ipython
Requires-Dist: zmq
Requires-Dist: ipykernel
Requires-Dist: polars
Requires-Dist: pyarrow
